[
  {
    "id": "ad49a405-97a0-4866-9106-fc46720e3575",
    "title": "Rename this",
    "kind": "beat",
    "children": [
      {
        "id": "15b5eac3-dfa6-4db7-92c1-3b99b68b70c1",
        "title": "New Milestone",
        "kind": "milestone",
        "children": []
      },
      {
        "id": "2802c73c-82cd-4738-b045-1bc9df97ace8",
        "title": "new child",
        "kind": "chapter",
        "children": []
      }
    ]
  },
  {
    "id": "0a144387-8ae3-42ed-a392-16a54e506ff8",
    "title": "Middle",
    "kind": "beat",
    "children": [
      {
        "id": "bf57c69f-a9bd-483a-b7b2-7aa5a70bd306",
        "title": "expand me",
        "kind": "chapter",
        "children": []
      }
    ]
  },
  {
    "id": "3f0f2f81-2e4b-40d4-bfa7-3d156ed1240c",
    "title": "End",
    "kind": "beat",
    "children": [
      {
        "id": "f7409bef-d800-4ba2-a7bc-1e3f938bc5ff",
        "title": "new child",
        "kind": "chapter",
        "children": [
          {
            "id": "4fd012f8-c888-4a08-9879-10a5b14f8575",
            "title": "rename this milestone",
            "kind": "milestone",
            "children": []
          }
        ]
      }
    ]
  },
  {
    "id": "8a273d95-0da1-4f10-b5c6-cb6130bb0e12",
    "title": "the new beat",
    "kind": "beat",
    "children": [
      {
        "id": "1e872eb6-1b31-48da-afd6-6373dd7ccdb0",
        "title": "rename this chapter",
        "kind": "chapter",
        "children": [
          {
            "id": "3e9981f9-dc9a-4e13-b4a9-5c033aadea5e",
            "title": "rename this node",
            "kind": "milestone",
            "children": []
          }
        ]
      }
    ]
  },
  {
    "id": "0a34175a-5d21-443a-9b64-353833a88bcc",
    "title": "the last chapter",
    "kind": "chapter",
    "children": [
      {
        "id": "98674240-d14d-4928-98da-fd56206b63d6",
        "title": "sibling 1",
        "kind": "chapter",
        "children": []
      },
      {
        "id": "30eb2236-e4f2-4f17-8c98-baebb1fd99ed",
        "title": "next child",
        "kind": "chapter",
        "children": [
          {
            "id": "cdf47a42-5144-4b02-aa11-78b6abd1efc7",
            "title": "the last milestone of all",
            "kind": "milestone",
            "children": []
          },
          {
            "id": "75de4de4-484b-4581-87ed-a821d2023c3e",
            "title": "last milestone ever",
            "kind": "milestone",
            "children": []
          }
        ]
      },
      {
        "id": "d85f3f60-3e0e-42e8-b9f2-33ecb68cfaa0",
        "title": "sibling 2",
        "kind": "chapter",
        "children": [
          {
            "id": "14cf9bf8-7041-4b50-b02f-6951ff56dd63",
            "title": "mile 1",
            "kind": "milestone",
            "children": []
          },
          {
            "id": "b99edebc-9970-4919-b03c-2229762355ef",
            "title": "mile 2",
            "kind": "milestone",
            "children": []
          },
          {
            "id": "891b0496-88c0-4496-8219-9f493d9234c4",
            "title": "mile 3",
            "kind": "milestone",
            "children": []
          }
        ]
      }
    ]
  }
]
